controlunit.vhd
library IEEE;
use IEEE.std_logic_1164.all;
use IEEE.numeric_std.all;

entity ControlUnit is
    port (
        opcode: in STD_LOGIC_VECTOR(15 downto 12);
        cRegWrite: out STD_LOGIC;
        cOffset: out STD_LOGIC;
        cALUOp: out STD_LOGIC_VECTOR(3 downto 0);
        cMemWrite: out STD_LOGIC;
        cMemRead: out STD_LOGIC;
        cMemToReg: out STD_LOGIC;
        cLdi: out STD_LOGIC;
        cJalr: out STD_LOGIC;
        reset: in STD_LOGIC
    );
end ControlUnit;

architecture Behavioral of ControlUnit is
    
begin
    process (reset, opcode)
    begin
        if (reset = '1') then
            cRegWrite <= '0';
            cOffset <= '0';
            cALUOp <= "0000";
            cMemWrite <= '0';
            cMemRead <= '0';
            cMemToReg <= '0';
            cLdi <= '0';
            cJalr <= '0';
        else
            cALUOp <= opcode;
            case opcode is
                when "0001" => -- ld
                    -- Loads from memory into rd
                    cRegWrite <= '1';
                    cOffset <= '0';
                    cMemWrite <= '0';
                    cMemRead <= '1';
                    cMemToReg <= '1'; -- Pass back memory
                    cLdi <= '0';
                    cJalr <= '0';
                when "0010" => -- ldi
                    -- Loads 8 bit immediate into rd
                    cRegWrite <= '1';
                    cOffset <= '0';
                    cMemWrite <= '0';
                    cMemRead <= '0';
                    cMemToReg <= 'X'; -- Ignored
                    cLdi <= '1';
                    cJalr <= '0';
                when "0011" => -- sd
                    -- Stores to memory
                    cRegWrite <= '0';
                    cOffset <= '0';
                    cMemWrite <= '1';
                    cMemRead <= '0';
                    cMemToReg <= '0';
                    cLdi <= '0';
                    cJalr <= '0';
                when "0100" | "0101" | "0110" | "0111" | "1000" | "1001" | "1010" => 
                    -- mv | add | sub | sll | srl | and | or
                    cRegWrite <= '1';
                    cOffset <= '0';
                    cMemWrite <= '0';
                    cMemRead <= '0';
                    cMemToReg <= '0'; -- Pass back ALU out
                    cLdi <= '0';
                    cJalr <= '0';
                when "1011" | "1100" | "1101" | "1110" =>
                    -- beq | blt | bge | jal
                    cRegWrite <= '1';
                    cOffset <= '1';
                    cMemWrite <= '0';
                    cMemRead <= '0';
                    cMemToReg <= '0';
                    cLdi <= '0';
                    cJalr <= '0';
                when "1111" =>
                    -- jalr
                    cRegWrite <= '1';
                    cOffset <= '1';
                    cMemWrite <= '0';
                    cMemRead <= '0';
                    cMemToReg <= '0';
                    cLdi <= '0';
                    cJalr <= '1';
                when others => -- halt
                    cRegWrite <= '0';
                    cOffset <= '0';
                    cMemWrite <= '0';
                    cMemRead <= '0';
                    cMemToReg <= '0';
                    cLdi <= '0';
                    cJalr <= '0';
            end case;
        end if;
    end process;
end Behavioral;

controlunit_tb.vhd
library IEEE;
use IEEE.std_logic_1164.all;
use IEEE.numeric_std.all;

entity t_controlunit is
end t_controlunit;

architecture behavior of t_controlunit is
    component ControlUnit is
        port (
            opcode: in STD_LOGIC_VECTOR(15 downto 12);
            cRegWrite: out STD_LOGIC;
            cOffset: out STD_LOGIC;
            cALUOp: out STD_LOGIC_VECTOR(3 downto 0);
            cMemWrite: out STD_LOGIC;
            cMemRead: out STD_LOGIC;
            cMemToReg: out STD_LOGIC;
            cLdi: out STD_LOGIC;
            cJalr: out STD_LOGIC;
            reset: in STD_LOGIC
        );
    end component ControlUnit;

    signal opcode_t: STD_LOGIC_VECTOR(15 downto 12);
    signal cRegWrite_t: STD_LOGIC;
    signal cOffset_t: STD_LOGIC;
    signal cALUOp_t: STD_LOGIC_VECTOR(3 downto 0);
    signal cMemWrite_t: STD_LOGIC;
    signal cMemRead_t: STD_LOGIC;
    signal cMemToReg_t: STD_LOGIC;
    signal cLdi_t: STD_LOGIC;
    signal cJalr_t: STD_LOGIC;
    signal reset_t : STD_LOGIC;

    begin
        control: ControlUnit
        port map (
            opcode => opcode_t,
            cRegWrite => cRegWrite_t,
            cOffset => cOffset_t,
            cALUOp => cALUOp_t,
            cMemWrite => cMemWrite_t,
            cMemRead => cMemRead_t,
            cMemToReg => cMemToReg_t,
            cLdi => cLdi_t,
            cJalr => cJalr_t,
            reset => reset_t
        );
        process
        begin
            -- Test reset
            reset_t <= '1';
            wait for 1 ms;
            reset_t <= '0';
            assert cALUOp_t <= "0000";
            wait for 1 ms;

            -- Test ld
            opcode_t <= "0001";
            wait for 1 ms;
            assert cMemRead_t = '1';
            assert cMemToReg_t = '1';
            wait for 1 ms; 

            -- Test ldi
            opcode_t <= "0010";
            assert cMemRead_t = '1';
            assert cMemToReg_t = '1';
            wait for 1 ms;

            -- Test sd
            opcode_t <= "0011";
            assert cMemWrite_t <= '1';

            -- Test arithmetic type
            for A in 4 to 10 loop
                opcode_t <= STD_LOGIC_VECTOR(to_unsigned(A, 4));
                assert cRegWrite_t <= '1';
                wait for 1 ms;
            end loop;

            -- Test branches and jumps
            for A in 11 to 15 loop
                opcode_t <= STD_LOGIC_VECTOR(to_unsigned(A, 4));
                assert cRegWrite_t <= '1';
                assert cOffset_t <= '1';
                wait for 1 ms;
            end loop;

            report "Test complete";
        end process;
end behavior;

controlunit.vcd
$date
  Wed Apr  1 13:56:42 2020
$end
$version
  GHDL v0
$end
$timescale
  1 fs
$end
$scope module standard $end
$upscope $end
$scope module std_logic_1164 $end
$upscope $end
$scope module numeric_std $end
$upscope $end
$scope module t_controlunit $end
$var reg 4 ! opcode_t[15:12] $end
$var reg 1 " cregwrite_t $end
$var reg 1 # coffset_t $end
$var reg 4 $ caluop_t[3:0] $end
$var reg 1 % cmemwrite_t $end
$var reg 1 & cmemread_t $end
$var reg 1 ' cmemtoreg_t $end
$var reg 1 ( cldi_t $end
$var reg 1 ) cjalr_t $end
$var reg 1 * reset_t $end
$scope module control $end
$var reg 4 + opcode[15:12] $end
$var reg 1 , cregwrite $end
$var reg 1 - coffset $end
$var reg 4 . caluop[3:0] $end
$var reg 1 / cmemwrite $end
$var reg 1 0 cmemread $end
$var reg 1 1 cmemtoreg $end
$var reg 1 2 cldi $end
$var reg 1 3 cjalr $end
$var reg 1 4 reset $end
$upscope $end
$upscope $end
$enddefinitions $end
#0
bUUUU !
0"
0#
b0000 $
0%
0&
0'
0(
0)
1*
bUUUU +
0,
0-
b0000 .
0/
00
01
02
03
14
#1000000000000
bUUUU $
0*
bUUUU .
04
#2000000000000
b0001 !
1"
b0001 $
1&
1'
b0001 +
1,
b0001 .
10
11
#3000000000000
#4000000000000
b0010 !
b0010 $
0&
X'
1(
b0010 +
b0010 .
00
X1
12
#5000000000000
b0100 !
b0100 $
0'
0(
b0100 +
b0100 .
01
02
#6000000000000
b0101 !
b0101 $
b0101 +
b0101 .
#7000000000000
b0110 !
b0110 $
b0110 +
b0110 .
#8000000000000
b0111 !
b0111 $
b0111 +
b0111 .
#9000000000000
b1000 !
b1000 $
b1000 +
b1000 .
#10000000000000
b1001 !
b1001 $
b1001 +
b1001 .
