memory.vhd
library IEEE;
use IEEE.std_logic_1164.all;
use IEEE.numeric_std.all;

entity Memory is
    port (
        ADDR: in STD_LOGIC_VECTOR(9 downto 0);
        DIN: in STD_LOGIC_VECTOR(15 downto 0);
        cMemWrite: in STD_LOGIC;
        cMemRead: in STD_LOGIC;
        outMemory: out STD_LOGIC_VECTOR(15 downto 0);
        reset: in STD_LOGIC := '0'
    );
end Memory;

architecture Behavioral of Memory is
    subtype word is STD_LOGIC_VECTOR(15 downto 0);
    type mem is array (0 to 1023) of word;
    signal memory1024: mem := (others => "0000000000000000");
begin
    -- Main block
    process (reset, ADDR, DIN, cMemWrite, cMemRead)
    begin
        if (reset = '1') then
            memory1024 <= (others => "0000000000000000");
            outMemory <= "0000000000000000";
        else
            if (cMemRead = '1') then
                outMemory <= memory1024(to_integer(unsigned(ADDR)));
            end if;
            if (cMemWrite = '1') then
                memory1024(to_integer(unsigned(ADDR))) <= DIN;
            end if;
            if (cMemRead = '0' and cMemWrite = '0') then
                -- Pass through DIN
                -- Useful for ldi and mv instructions
                outMemory <= DIN;
                report "cmem0";
            end if;
        end if;
        
    end process;

end Behavioral;

Part3/Memory/memory_tb.vhd
library IEEE;
use IEEE.std_logic_1164.all;
use IEEE.numeric_std.all;

entity t_memory is
end t_memory;

architecture behavior of t_memory is
    component Memory is
        port (
            ADDR: in STD_LOGIC_VECTOR(9 downto 0);
            DIN: in STD_LOGIC_VECTOR(15 downto 0);
            cMemWrite: in STD_LOGIC;
            cMemRead: in STD_LOGIC;
            outMemory: out STD_LOGIC_VECTOR(15 downto 0);
            reset: in STD_LOGIC := '0'
        );
    end component Memory;

    signal ADDR_t: STD_LOGIC_VECTOR(9 downto 0);
    signal DIN_t: STD_LOGIC_VECTOR(15 downto 0);
    signal cMemWrite_t: STD_LOGIC;
    signal cMemRead_t: STD_LOGIC;
    signal outMemory_t: STD_LOGIC_VECTOR(15 downto 0); 
    signal reset_t: STD_LOGIC;

    begin
        mem: Memory
        port map(
            ADDR => ADDR_t,
            DIN => DIN_t,
            cMemWrite => cMemWrite_t,
            cMemRead => cMemRead_t,
            outMemory => outMemory_t,
            reset => reset_t
        );
        process
        begin
            -- Test reset
            reset_t <= '1';
            wait for 1 ms;
            reset_t <= '0';
            wait for 1 ms;
            
            -- Test mem read/write
            cMemWrite_t <= '1';
            cMemRead_t <= '0';
            ADDR_t <= "1010101010"; -- Address 682
            DIN_t <= "1000000000000000"; -- 32768
            wait for 1 ms;
            cMemWrite_t <= '0';
            cMemRead_t <= '1';
            ADDR_t <= "1010101010";
            wait for 1 ms;
            assert outMemory_t = DIN_t;

            -- Test passthrough
            cMemRead_t <= '0';
            cMemWrite_t <= '0';
            wait for 1 ms;
            assert outMemory_t = DIN_t;

        end process;

end behavior;

Memory/memory.vcd
$date
  Wed Mar 18 11:26:33 2020
$end
$version
  GHDL v0
$end
$timescale
  1 fs
$end
$scope module standard $end
$upscope $end
$scope module std_logic_1164 $end
$upscope $end
$scope module numeric_std $end
$upscope $end
$scope module t_memory $end
$var reg 10 ! addr_t[9:0] $end
$var reg 16 " din_t[15:0] $end
$var reg 1 # cmemwrite_t $end
$var reg 1 $ cmemread_t $end
$var reg 16 % outmemory_t[15:0] $end
$var reg 1 & reset_t $end
$scope module mem $end
$var reg 10 ' addr[9:0] $end
$var reg 16 ( din[15:0] $end
$var reg 1 ) cmemwrite $end
$var reg 1 * cmemread $end
$var reg 16 + outmemory[15:0] $end
$var reg 1 , reset $end
$comment memory1024 is not handled $end
$upscope $end
$upscope $end
$enddefinitions $end
#0
bUUUUUUUUUU !
bUUUUUUUUUUUUUUUU "
U#
U$
b0000000000000000 %
1&
bUUUUUUUUUU '
bUUUUUUUUUUUUUUUU (
U)
U*
b0000000000000000 +
1,
#1000000000000
0&
0,
#2000000000000
b1010101010 !
b1000000000000000 "
1#
0$
b1010101010 '
b1000000000000000 (
1)
0*
#3000000000000
0#
1$
b1000000000000000 %
0)
1*
b1000000000000000 +
#4000000000000
0$
0*
#5000000000000
b0000000000000000 %
1&
b0000000000000000 +
1,
#6000000000000
b1000000000000000 %
0&
b1000000000000000 +
0,
#7000000000000
1#
1)
#8000000000000
0#
1$
0)
1*
#9000000000000
0$
0*
#10000000000000
b0000000000000000 %
1&
b0000000000000000 +
1,
#11000000000000
b1000000000000000 %
0&
b1000000000000000 +
0,
#12000000000000
1#
1)
#13000000000000
0#
1$
0)
1*
#14000000000000
0$
0*
#15000000000000
b0000000000000000 %
1&
b0000000000000000 +
1,
#16000000000000
b1000000000000000 %
0&
b1000000000000000 +
0,
#17000000000000
1#
1)
#18000000000000
0#
1$
0)
1*
#19000000000000
0$
0*
#20000000000000
b0000000000000000 %
1&
b0000000000000000 +
1,
#21000000000000
b1000000000000000 %
0&
b1000000000000000 +
0,
#22000000000000
1#
1)
#23000000000000
0#
1$
0)
1*
#24000000000000
0$
0*
#25000000000000
b0000000000000000 %
1&
b0000000000000000 +
1,
#26000000000000
b1000000000000000 %
0&
b1000000000000000 +
0,
#27000000000000
1#
1)
#28000000000000
0#
1$
0)
1*
#29000000000000
0$
0*
#30000000000000
b0000000000000000 %
1&
b0000000000000000 +
1,
#31000000000000
b1000000000000000 %
0&
b1000000000000000 +
0,
#32000000000000
1#
1)
#33000000000000
0#
1$
0)
1*
#34000000000000
0$
0*
#35000000000000
b0000000000000000 %
1&
b0000000000000000 +
1,
#36000000000000
b1000000000000000 %
0&
b1000000000000000 +
0,
#37000000000000
1#
1)
#38000000000000
0#
1$
0)
1*
#39000000000000
0$
0*
#40000000000000
b0000000000000000 %
1&
b0000000000000000 +
1,
#41000000000000
b1000000000000000 %
0&
b1000000000000000 +
0,
#42000000000000
1#
1)
#43000000000000
0#
1$
0)
1*
#44000000000000
0$
0*
#45000000000000
b0000000000000000 %
1&
b0000000000000000 +
1,
#46000000000000
b1000000000000000 %
0&
b1000000000000000 +
0,
#47000000000000
1#
1)
#48000000000000
0#
1$
0)
1*
#49000000000000
0$
0*
#50000000000000
b0000000000000000 %
1&
b0000000000000000 +
1,
#51000000000000
b1000000000000000 %
0&
b1000000000000000 +
0,
#52000000000000
1#
1)
#53000000000000
0#
1$
0)
1*
#54000000000000
0$
0*
#55000000000000
b0000000000000000 %
1&
b0000000000000000 +
1,
#56000000000000
b1000000000000000 %
0&
b1000000000000000 +
0,
#57000000000000
1#
1)
#58000000000000
0#
1$
0)
1*
#59000000000000
0$
0*
#60000000000000
b0000000000000000 %
1&
b0000000000000000 +
1,
#61000000000000
b1000000000000000 %
0&
b1000000000000000 +
0,
#62000000000000
1#
1)
#63000000000000
0#
1$
0)
1*
#64000000000000
0$
0*
#65000000000000
b0000000000000000 %
1&
b0000000000000000 +
1,
#66000000000000
b1000000000000000 %
0&
b1000000000000000 +
0,
#67000000000000
1#
1)
#68000000000000
0#
1$
0)
1*
#69000000000000
0$
0*
#70000000000000
b0000000000000000 %
1&
b0000000000000000 +
1,
#71000000000000
b1000000000000000 %
0&
b1000000000000000 +
0,
#72000000000000
1#
1)
#73000000000000
0#
1$
0)
1*
#74000000000000
0$
0*
#75000000000000
b0000000000000000 %
1&
b0000000000000000 +
1,
#76000000000000
b1000000000000000 %
0&
b1000000000000000 +
0,
#77000000000000
1#
1)
#78000000000000
0#
1$
0)
1*
#79000000000000
0$
0*
#80000000000000
b0000000000000000 %
1&
b0000000000000000 +
1,
#81000000000000
b1000000000000000 %
0&
b1000000000000000 +
0,
#82000000000000
1#
1)
#83000000000000
0#
1$
0)
1*
#84000000000000
0$
0*
#85000000000000
b0000000000000000 %
1&
b0000000000000000 +
1,
#86000000000000
b1000000000000000 %
0&
b1000000000000000 +
0,
#87000000000000
1#
1)
#88000000000000
0#
1$
0)
1*
#89000000000000
0$
0*
#90000000000000
b0000000000000000 %
1&
b0000000000000000 +
1,
#91000000000000
b1000000000000000 %
0&
b1000000000000000 +
0,
#92000000000000
1#
1)
#93000000000000
0#
1$
0)
1*
#94000000000000
0$
0*
#95000000000000
b0000000000000000 %
1&
b0000000000000000 +
1,
#96000000000000
b1000000000000000 %
0&
b1000000000000000 +
0,
#97000000000000
1#
1)
#98000000000000
0#
1$
0)
1*
#99000000000000
0$
0*
#100000000000000
b0000000000000000 %
1&
b0000000000000000 +
1,
