Test/func.vhd
library IEEE;
use IEEE.std_logic_1164.all;

entity func is
	port(
		I	: in  std_logic_vector(3 downto 0);
        Y	: out std_logic);
end func;

architecture behaviour of func is
begin	
	process (I)
	begin
		case (I) is
			when "0000" => Y <= '1';
			when "0001" => Y <= '1';
			when "0100" => Y <= '1';
			when "1001" => Y <= '1';
			when "1110" => Y <= '1';
			when others => Y <= '0';
		end case;
	end process;
end behaviour;

Test/func_tb.vhd
library IEEE;
use IEEE.std_logic_1164.all;

entity t_func is
end t_func;

architecture t_behaviour of t_func is

	component func is
		port(
			I		: in std_logic_vector(3 downto 0);
			Y		: out std_logic);
	end component func;

	signal I_t		: std_logic_vector(3 downto 0);
	signal Y_t		: std_logic;

	begin	

		module_func: func
		port map (
				I => I_t,
				Y => Y_t
				);
		--
		process
			begin
				
				-- inputs which produce '1' on the output
				
				I_t <= "0000";	--0
				wait for 1 ms;
				I_t <= "0001";	--1
				wait for 1 ms;
				I_t <= "0100";	--4
				wait for 1 ms;
				I_t <= "1001";	--9
				wait for 1 ms;
				I_t <= "1110";	--14
				wait for 1 ms;
				
				-- other inputs
				
				I_t <= "0010";	--2
				wait for 1 ms;
				I_t <= "0011";	--3
				wait for 1 ms;
				I_t <= "0101";	--5
				wait for 1 ms;
				I_t <= "0110";	--6
				wait for 1 ms;
				I_t <= "0111";	--7
				wait for 1 ms;
				I_t <= "1000";	--8
				wait for 1 ms;
				I_t <= "1010";	--10
				wait for 1 ms;
				I_t <= "1011";	--11
				wait for 1 ms;
				I_t <= "1100";	--12
				wait for 1 ms;
				I_t <= "1101";	--13
				wait for 1 ms;
				I_t <= "1111";	--15
				wait for 1 ms;
				wait;
			end process;
		--
	--
--
end t_behaviour;

Part3/Testbench/func.vcd
$date
  Thu Mar  5 09:35:34 2020
$end
$version
  GHDL v0
$end
$timescale
  1 fs
$end
$scope module standard $end
$upscope $end
$scope module std_logic_1164 $end
$upscope $end
$scope module t_func $end
$var reg 4 ! i_t[3:0] $end
$var reg 1 " y_t $end
$scope module module_func $end
$var reg 4 # i[3:0] $end
$var reg 1 $ y $end
$upscope $end
$upscope $end
$enddefinitions $end
#0
b0000 !
1"
b0000 #
1$
#1000000000000
b0001 !
b0001 #
#2000000000000
b0100 !
b0100 #
#3000000000000
b1001 !
b1001 #
#4000000000000
b1110 !
b1110 #
#5000000000000
b0010 !
0"
b0010 #
0$
#6000000000000
b0011 !
b0011 #
#7000000000000
b0101 !
b0101 #
#8000000000000
b0110 !
b0110 #
#9000000000000
b0111 !
b0111 #
#10000000000000
b1000 !
b1000 #
#11000000000000
b1010 !
b1010 #
#12000000000000
b1011 !
b1011 #
#13000000000000
b1100 !
b1100 #
#14000000000000
b1101 !
b1101 #
#15000000000000
b1111 !
b1111 #
