Part3/Memory/memory.vhd
library IEEE;
use IEEE.std_logic_1164.all;
use IEEE.numeric_std.all;

entity Memory is
    port (
        ADDR: in STD_LOGIC_VECTOR(9 downto 0);
        DIN: in STD_LOGIC_VECTOR(15 downto 0);
        cMemWrite: in STD_LOGIC;
        cMemRead: in STD_LOGIC;
        outMemory: out STD_LOGIC_VECTOR(15 downto 0);
        reset: in STD_LOGIC := '0'
    );
end Memory;

architecture Behavioral of Memory is
    subtype word is STD_LOGIC_VECTOR(15 downto 0);
    type mem is array (0 to 1023) of word;
    signal memory1024: mem := (others => "0000000000000000");
begin
    -- Main block
    process (reset, ADDR, DIN, cMemWrite, cMemRead)
    begin
        if (reset = '1') then
            memory1024 <= (others => "0000000000000000");
            outMemory <= "0000000000000000";
            report "reset on";
        else
            if (cMemRead = '1') then
                outMemory <= memory1024(to_integer(unsigned(ADDR)));
            end if;
            if (cMemWrite = '1') then
                memory1024(to_integer(unsigned(ADDR))) <= DIN;
            end if;
            if (cMemRead = '0' and cMemWrite = '0') then
                -- Pass through DIN
                -- Useful for ldi and mv instructions
                outMemory <= DIN;
            end if;
            report "reset off";
        end if;
        
    end process;

end Behavioral;

Part3/Memory/memory_tb.vhd
library IEEE;
use IEEE.std_logic_1164.all;
use IEEE.numeric_std.all;

entity t_memory is
end t_memory;

architecture behavior of t_memory is
    component Memory is
        port (
            ADDR: in STD_LOGIC_VECTOR(9 downto 0);
            DIN: in STD_LOGIC_VECTOR(15 downto 0);
            cMemWrite: in STD_LOGIC;
            cMemRead: in STD_LOGIC;
            outMemory: out STD_LOGIC_VECTOR(15 downto 0);
            reset: in STD_LOGIC := '0'
        );
    end component Memory;

    signal ADDR_t: STD_LOGIC_VECTOR(9 downto 0);
    signal DIN_t: STD_LOGIC_VECTOR(15 downto 0);
    signal cMemWrite_t: STD_LOGIC;
    signal cMemRead_t: STD_LOGIC;
    signal outMemory_t: STD_LOGIC_VECTOR(15 downto 0); 
    signal reset_t: STD_LOGIC;

    begin
        mem: Memory
        port map(
            ADDR => ADDR_t,
            DIN => DIN_t,
            cMemWrite => cMemWrite_t,
            cMemRead => cMemRead_t,
            outMemory => outMemory_t,
            reset => reset_t
        );
        process
        begin
            -- Test reset
            reset_t <= '1';
            wait for 1 ms;
            reset_t <= '0';
            wait for 1 ms;
            
            -- Test mem read/write
            cMemWrite_t <= '1';
            ADDR_t <= "1010101010"; -- Address 682
            DIN_t <= "1000000000000000"; -- 32768
            wait for 1 ms;
            cMemWrite_t <= '0';
            cMemRead_t <= '1';
            ADDR_t <= "1010101010";
            wait for 1 ms;
            assert outMemory_t = DIN_t;

        end process;
            

end behavior;

Part3/Memory/memory.vcd
$date
  Thu Mar 12 20:39:30 2020
$end
$version
  GHDL v0
$end
$timescale
  1 fs
$end
$scope module standard $end
$upscope $end
$scope module std_logic_1164 $end
$upscope $end
$scope module numeric_std $end
$upscope $end
$scope module t_memory $end
$var reg 10 ! addr_t[9:0] $end
$var reg 16 " din_t[15:0] $end
$var reg 1 # cmemwrite_t $end
$var reg 1 $ cmemread_t $end
$var reg 16 % outmemory_t[15:0] $end
$var reg 1 & reset_t $end
$scope module mem $end
$var reg 10 ' addr[9:0] $end
$var reg 16 ( din[15:0] $end
$var reg 1 ) cmemwrite $end
$var reg 1 * cmemread $end
$var reg 16 + outmemory[15:0] $end
$var reg 1 , reset $end
$comment memory1024 is not handled $end
$upscope $end
$upscope $end
$enddefinitions $end
#0
bUUUUUUUUUU !
bUUUUUUUUUUUUUUUU "
U#
U$
b0000000000000000 %
1&
bUUUUUUUUUU '
bUUUUUUUUUUUUUUUU (
U)
U*
b0000000000000000 +
1,
#1000000000000
0&
0,
#2000000000000
b1010101010 !
b1000000000000000 "
1#
b1010101010 '
b1000000000000000 (
1)
#3000000000000
0#
1$
b1000000000000000 %
0)
1*
b1000000000000000 +
#4000000000000
b0000000000000000 %
1&
b0000000000000000 +
1,
#5000000000000
0&
0,
#6000000000000
1#
1)
#7000000000000
0#
b1000000000000000 %
0)
b1000000000000000 +
#8000000000000
b0000000000000000 %
1&
b0000000000000000 +
1,
#9000000000000
0&
0,
#10000000000000
1#
1)
#11000000000000
0#
b1000000000000000 %
0)
b1000000000000000 +
#12000000000000
b0000000000000000 %
1&
b0000000000000000 +
1,
#13000000000000
0&
0,
#14000000000000
1#
1)
#15000000000000
0#
b1000000000000000 %
0)
b1000000000000000 +
#16000000000000
b0000000000000000 %
1&
b0000000000000000 +
1,
#17000000000000
0&
0,
#18000000000000
1#
1)
#19000000000000
0#
b1000000000000000 %
0)
b1000000000000000 +
#20000000000000
b0000000000000000 %
1&
b0000000000000000 +
1,
#21000000000000
0&
0,
#22000000000000
1#
1)
#23000000000000
0#
b1000000000000000 %
0)
b1000000000000000 +
#24000000000000
b0000000000000000 %
1&
b0000000000000000 +
1,
#25000000000000
0&
0,
#26000000000000
1#
1)
#27000000000000
0#
b1000000000000000 %
0)
b1000000000000000 +
#28000000000000
b0000000000000000 %
1&
b0000000000000000 +
1,
#29000000000000
0&
0,
#30000000000000
1#
1)
#31000000000000
0#
b1000000000000000 %
0)
b1000000000000000 +
#32000000000000
b0000000000000000 %
1&
b0000000000000000 +
1,
#33000000000000
0&
0,
#34000000000000
1#
1)
#35000000000000
0#
b1000000000000000 %
0)
b1000000000000000 +
#36000000000000
b0000000000000000 %
1&
b0000000000000000 +
1,
#37000000000000
0&
0,
#38000000000000
1#
1)
#39000000000000
0#
b1000000000000000 %
0)
b1000000000000000 +
#40000000000000
b0000000000000000 %
1&
b0000000000000000 +
1,
#41000000000000
0&
0,
#42000000000000
1#
1)
#43000000000000
0#
b1000000000000000 %
0)
b1000000000000000 +
#44000000000000
b0000000000000000 %
1&
b0000000000000000 +
1,
#45000000000000
0&
0,
#46000000000000
1#
1)
#47000000000000
0#
b1000000000000000 %
0)
b1000000000000000 +
#48000000000000
b0000000000000000 %
1&
b0000000000000000 +
1,
#49000000000000
0&
0,
#50000000000000
1#
1)
#51000000000000
0#
b1000000000000000 %
0)
b1000000000000000 +
#52000000000000
b0000000000000000 %
1&
b0000000000000000 +
1,
#53000000000000
0&
0,
#54000000000000
1#
1)
#55000000000000
0#
b1000000000000000 %
0)
b1000000000000000 +
#56000000000000
b0000000000000000 %
1&
b0000000000000000 +
1,
#57000000000000
0&
0,
#58000000000000
1#
1)
#59000000000000
0#
b1000000000000000 %
0)
b1000000000000000 +
#60000000000000
b0000000000000000 %
1&
b0000000000000000 +
1,
#61000000000000
0&
0,
#62000000000000
1#
1)
#63000000000000
0#
b1000000000000000 %
0)
b1000000000000000 +
#64000000000000
b0000000000000000 %
1&
b0000000000000000 +
1,
#65000000000000
0&
0,
#66000000000000
1#
1)
#67000000000000
0#
b1000000000000000 %
0)
b1000000000000000 +
#68000000000000
b0000000000000000 %
1&
b0000000000000000 +
1,
#69000000000000
0&
0,
#70000000000000
1#
1)
#71000000000000
0#
b1000000000000000 %
0)
b1000000000000000 +
#72000000000000
b0000000000000000 %
1&
b0000000000000000 +
1,
#73000000000000
0&
0,
#74000000000000
1#
1)
#75000000000000
0#
b1000000000000000 %
0)
b1000000000000000 +
#76000000000000
b0000000000000000 %
1&
b0000000000000000 +
1,
#77000000000000
0&
0,
#78000000000000
1#
1)
#79000000000000
0#
b1000000000000000 %
0)
b1000000000000000 +
#80000000000000
b0000000000000000 %
1&
b0000000000000000 +
1,
#81000000000000
0&
0,
#82000000000000
1#
1)
#83000000000000
0#
b1000000000000000 %
0)
b1000000000000000 +
#84000000000000
b0000000000000000 %
1&
b0000000000000000 +
1,
#85000000000000
0&
0,
#86000000000000
1#
1)
#87000000000000
0#
b1000000000000000 %
0)
b1000000000000000 +
#88000000000000
b0000000000000000 %
1&
b0000000000000000 +
1,
#89000000000000
0&
0,
#90000000000000
1#
1)
#91000000000000
0#
b1000000000000000 %
0)
b1000000000000000 +
#92000000000000
b0000000000000000 %
1&
b0000000000000000 +
1,
#93000000000000
0&
0,
#94000000000000
1#
1)
#95000000000000
0#
b1000000000000000 %
0)
b1000000000000000 +
#96000000000000
b0000000000000000 %
1&
b0000000000000000 +
1,
#97000000000000
0&
0,
#98000000000000
1#
1)
#99000000000000
0#
b1000000000000000 %
0)
b1000000000000000 +
#100000000000000
b0000000000000000 %
1&
b0000000000000000 +
1,
#101000000000000
0&
0,
#102000000000000
1#
1)
#103000000000000
0#
b1000000000000000 %
0)
b1000000000000000 +
#104000000000000
b0000000000000000 %
1&
b0000000000000000 +
1,
#105000000000000
0&
0,
#106000000000000
1#
1)
#107000000000000
0#
b1000000000000000 %
0)
b1000000000000000 +
#108000000000000
b0000000000000000 %
1&
b0000000000000000 +
1,
#109000000000000
0&
0,
#110000000000000
1#
1)
#111000000000000
0#
b1000000000000000 %
0)
b1000000000000000 +
#112000000000000
b0000000000000000 %
1&
b0000000000000000 +
1,
#113000000000000
0&
0,
#114000000000000
1#
1)
#115000000000000
0#
b1000000000000000 %
0)
b1000000000000000 +
#116000000000000
b0000000000000000 %
1&
b0000000000000000 +
1,
#117000000000000
0&
0,
#118000000000000
1#
1)
#119000000000000
0#
b1000000000000000 %
0)
b1000000000000000 +
#120000000000000
b0000000000000000 %
1&
b0000000000000000 +
1,
#121000000000000
0&
0,
#122000000000000
1#
1)
#123000000000000
0#
b1000000000000000 %
0)
b1000000000000000 +
#124000000000000
b0000000000000000 %
1&
b0000000000000000 +
1,
#125000000000000
0&
0,
#126000000000000
1#
1)
#127000000000000
0#
b1000000000000000 %
0)
b1000000000000000 +
#128000000000000
b0000000000000000 %
1&
b0000000000000000 +
1,
#129000000000000
0&
0,
#130000000000000
1#
1)
#131000000000000
0#
b1000000000000000 %
0)
b1000000000000000 +
#132000000000000
b0000000000000000 %
1&
b0000000000000000 +
1,
#133000000000000
0&
0,
#134000000000000
1#
1)
#135000000000000
0#
b1000000000000000 %
0)
b1000000000000000 +
#136000000000000
b0000000000000000 %
1&
b0000000000000000 +
1,
#137000000000000
0&
0,
#138000000000000
1#
1)
#139000000000000
0#
b1000000000000000 %
0)
b1000000000000000 +
#140000000000000
b0000000000000000 %
1&
b0000000000000000 +
1,
#141000000000000
0&
0,
#142000000000000
1#
1)
#143000000000000
0#
b1000000000000000 %
0)
b1000000000000000 +
#144000000000000
b0000000000000000 %
1&
b0000000000000000 +
1,
#145000000000000
0&
0,
#146000000000000
1#
1)
#147000000000000
0#
b1000000000000000 %
0)
b1000000000000000 +
#148000000000000
b0000000000000000 %
1&
b0000000000000000 +
1,
#149000000000000
0&
0,
#150000000000000
1#
1)
#151000000000000
0#
b1000000000000000 %
0)
b1000000000000000 +
#152000000000000
b0000000000000000 %
1&
b0000000000000000 +
1,
#153000000000000
0&
0,
#154000000000000
1#
1)
#155000000000000
0#
b1000000000000000 %
0)
b1000000000000000 +
#156000000000000
b0000000000000000 %
1&
b0000000000000000 +
1,
#157000000000000
0&
0,
#158000000000000
1#
1)
#159000000000000
0#
b1000000000000000 %
0)
b1000000000000000 +
#160000000000000
b0000000000000000 %
1&
b0000000000000000 +
1,
#161000000000000
0&
0,
#162000000000000
1#
1)
#163000000000000
0#
b1000000000000000 %
0)
b1000000000000000 +
#164000000000000
b0000000000000000 %
1&
b0000000000000000 +
1,
#165000000000000
0&
0,
#166000000000000
1#
1)
#167000000000000
0#
b1000000000000000 %
0)
b1000000000000000 +
#168000000000000
b0000000000000000 %
1&
b0000000000000000 +
1,
#169000000000000
0&
0,
#170000000000000
1#
1)
#171000000000000
0#
b1000000000000000 %
0)
b1000000000000000 +
#172000000000000
b0000000000000000 %
1&
b0000000000000000 +
1,
#173000000000000
0&
0,
#174000000000000
1#
1)
#175000000000000
0#
b1000000000000000 %
0)
b1000000000000000 +
#176000000000000
b0000000000000000 %
1&
b0000000000000000 +
1,
#177000000000000
0&
0,
#178000000000000
1#
1)
#179000000000000
0#
b1000000000000000 %
0)
b1000000000000000 +
#180000000000000
b0000000000000000 %
1&
b0000000000000000 +
1,
#181000000000000
0&
0,
#182000000000000
1#
1)
#183000000000000
0#
b1000000000000000 %
0)
b1000000000000000 +
#184000000000000
b0000000000000000 %
1&
b0000000000000000 +
1,
#185000000000000
0&
0,
#186000000000000
1#
1)
#187000000000000
0#
b1000000000000000 %
0)
b1000000000000000 +
#188000000000000
b0000000000000000 %
1&
b0000000000000000 +
1,
#189000000000000
0&
0,
#190000000000000
1#
1)
#191000000000000
0#
b1000000000000000 %
0)
b1000000000000000 +
#192000000000000
b0000000000000000 %
1&
b0000000000000000 +
1,
#193000000000000
0&
0,
#194000000000000
1#
1)
#195000000000000
0#
b1000000000000000 %
0)
b1000000000000000 +
#196000000000000
b0000000000000000 %
1&
b0000000000000000 +
1,
#197000000000000
0&
0,
#198000000000000
1#
1)
#199000000000000
0#
b1000000000000000 %
0)
b1000000000000000 +
#200000000000000
b0000000000000000 %
1&
b0000000000000000 +
1,
#201000000000000
0&
0,
#202000000000000
1#
1)
#203000000000000
0#
b1000000000000000 %
0)
b1000000000000000 +
#204000000000000
b0000000000000000 %
1&
b0000000000000000 +
1,
#205000000000000
0&
0,
#206000000000000
1#
1)
#207000000000000
0#
b1000000000000000 %
0)
b1000000000000000 +
#208000000000000
b0000000000000000 %
1&
b0000000000000000 +
1,
#209000000000000
0&
0,
#210000000000000
1#
1)
#211000000000000
0#
b1000000000000000 %
0)
b1000000000000000 +
#212000000000000
b0000000000000000 %
1&
b0000000000000000 +
1,
#213000000000000
0&
0,
#214000000000000
1#
1)
#215000000000000
0#
b1000000000000000 %
0)
b1000000000000000 +
#216000000000000
b0000000000000000 %
1&
b0000000000000000 +
1,
#217000000000000
0&
0,
#218000000000000
1#
1)
#219000000000000
0#
b1000000000000000 %
0)
b1000000000000000 +
#220000000000000
b0000000000000000 %
1&
b0000000000000000 +
1,
#221000000000000
0&
0,
#222000000000000
1#
1)
#223000000000000
0#
b1000000000000000 %
0)
b1000000000000000 +
#224000000000000
b0000000000000000 %
1&
b0000000000000000 +
1,
#225000000000000
0&
0,
#226000000000000
1#
1)
#227000000000000
0#
b1000000000000000 %
0)
b1000000000000000 +
#228000000000000
b0000000000000000 %
1&
b0000000000000000 +
1,
#229000000000000
0&
0,
#230000000000000
1#
1)
#231000000000000
0#
b1000000000000000 %
0)
b1000000000000000 +
#232000000000000
b0000000000000000 %
1&
b0000000000000000 +
1,
#233000000000000
0&
0,
#234000000000000
1#
1)
#235000000000000
0#
b1000000000000000 %
0)
b1000000000000000 +
#236000000000000
b0000000000000000 %
1&
b0000000000000000 +
1,
#237000000000000
0&
0,
#238000000000000
1#
1)
#239000000000000
0#
b1000000000000000 %
0)
b1000000000000000 +
#240000000000000
b0000000000000000 %
1&
b0000000000000000 +
1,
#241000000000000
0&
0,
#242000000000000
1#
1)
#243000000000000
0#
b1000000000000000 %
0)
b1000000000000000 +
#244000000000000
b0000000000000000 %
1&
b0000000000000000 +
1,
#245000000000000
0&
0,
#246000000000000
1#
1)
#247000000000000
0#
b1000000000000000 %
0)
b1000000000000000 +
#248000000000000
b0000000000000000 %
1&
b0000000000000000 +
1,
#249000000000000
0&
0,
#250000000000000
1#
1)
#251000000000000
0#
b1000000000000000 %
0)
b1000000000000000 +
#252000000000000
b0000000000000000 %
1&
b0000000000000000 +
1,
#253000000000000
0&
0,
#254000000000000
1#
1)
#255000000000000
0#
b1000000000000000 %
0)
b1000000000000000 +
#256000000000000
b0000000000000000 %
1&
b0000000000000000 +
1,
#257000000000000
0&
0,
#258000000000000
1#
1)
#259000000000000
0#
b1000000000000000 %
0)
b1000000000000000 +
#260000000000000
b0000000000000000 %
1&
b0000000000000000 +
1,
#261000000000000
0&
0,
#262000000000000
1#
1)
#263000000000000
0#
b1000000000000000 %
0)
b1000000000000000 +
#264000000000000
b0000000000000000 %
1&
b0000000000000000 +
1,
#265000000000000
0&
0,
#266000000000000
1#
1)
#267000000000000
0#
b1000000000000000 %
0)
b1000000000000000 +
#268000000000000
b0000000000000000 %
1&
b0000000000000000 +
1,
#269000000000000
0&
0,
#270000000000000
1#
1)
#271000000000000
0#
b1000000000000000 %
0)
b1000000000000000 +
#272000000000000
b0000000000000000 %
1&
b0000000000000000 +
1,
#273000000000000
0&
0,
#274000000000000
1#
1)
#275000000000000
0#
b1000000000000000 %
0)
b1000000000000000 +
#276000000000000
b0000000000000000 %
1&
b0000000000000000 +
1,
#277000000000000
0&
0,
#278000000000000
1#
1)
#279000000000000
0#
b1000000000000000 %
0)
b1000000000000000 +
#280000000000000
b0000000000000000 %
1&
b0000000000000000 +
1,
#281000000000000
0&
0,
#282000000000000
1#
1)
#283000000000000
0#
b1000000000000000 %
0)
b1000000000000000 +
#284000000000000
b0000000000000000 %
1&
b0000000000000000 +
1,
#285000000000000
0&
0,
#286000000000000
1#
1)
#287000000000000
0#
b1000000000000000 %
0)
b1000000000000000 +
#288000000000000
b0000000000000000 %
1&
b0000000000000000 +
1,
#289000000000000
0&
0,
#290000000000000
1#
1)
#291000000000000
0#
b1000000000000000 %
0)
b1000000000000000 +
#292000000000000
b0000000000000000 %
1&
b0000000000000000 +
1,
#293000000000000
0&
0,
#294000000000000
1#
1)
#295000000000000
0#
b1000000000000000 %
0)
b1000000000000000 +
#296000000000000
b0000000000000000 %
1&
b0000000000000000 +
1,
#297000000000000
0&
0,
#298000000000000
1#
1)
#299000000000000
0#
b1000000000000000 %
0)
b1000000000000000 +
#300000000000000
b0000000000000000 %
1&
b0000000000000000 +
1,
#301000000000000
0&
0,
#302000000000000
1#
1)
#303000000000000
0#
b1000000000000000 %
0)
b1000000000000000 +
#304000000000000
b0000000000000000 %
1&
b0000000000000000 +
1,
#305000000000000
0&
0,
#306000000000000
1#
1)
#307000000000000
0#
b1000000000000000 %
0)
b1000000000000000 +
#308000000000000
b0000000000000000 %
1&
b0000000000000000 +
1,
#309000000000000
0&
0,
#310000000000000
1#
1)
#311000000000000
0#
b1000000000000000 %
0)
b1000000000000000 +
#312000000000000
b0000000000000000 %
1&
b0000000000000000 +
1,
#313000000000000
0&
0,
#314000000000000
1#
1)
#315000000000000
0#
b1000000000000000 %
0)
b1000000000000000 +
#316000000000000
b0000000000000000 %
1&
b0000000000000000 +
1,
#317000000000000
0&
0,
#318000000000000
1#
1)
#319000000000000
0#
b1000000000000000 %
0)
b1000000000000000 +
#320000000000000
b0000000000000000 %
1&
b0000000000000000 +
1,
#321000000000000
0&
0,
#322000000000000
1#
1)
#323000000000000
0#
b1000000000000000 %
0)
b1000000000000000 +
#324000000000000
b0000000000000000 %
1&
b0000000000000000 +
1,
#325000000000000
0&
0,
#326000000000000
1#
1)
#327000000000000
0#
b1000000000000000 %
0)
b1000000000000000 +
#328000000000000
b0000000000000000 %
1&
b0000000000000000 +
1,
#329000000000000
0&
0,
#330000000000000
1#
1)
#331000000000000
0#
b1000000000000000 %
0)
b1000000000000000 +
#332000000000000
b0000000000000000 %
1&
b0000000000000000 +
1,
#333000000000000
0&
0,
#334000000000000
1#
1)
#335000000000000
0#
b1000000000000000 %
0)
b1000000000000000 +
#336000000000000
b0000000000000000 %
1&
b0000000000000000 +
1,
#337000000000000
0&
0,
#338000000000000
1#
1)
#339000000000000
0#
b1000000000000000 %
0)
b1000000000000000 +
#340000000000000
b0000000000000000 %
1&
b0000000000000000 +
1,
#341000000000000
0&
0,
#342000000000000
1#
1)
#343000000000000
0#
b1000000000000000 %
0)
b1000000000000000 +
#344000000000000
b0000000000000000 %
1&
b0000000000000000 +
1,
#345000000000000
0&
0,
#346000000000000
1#
1)
#347000000000000
0#
b1000000000000000 %
0)
b1000000000000000 +
#348000000000000
b0000000000000000 %
1&
b0000000000000000 +
1,
#349000000000000
0&
0,
#350000000000000
1#
1)
#351000000000000
0#
b1000000000000000 %
0)
b1000000000000000 +
#352000000000000
b0000000000000000 %
1&
b0000000000000000 +
1,
#353000000000000
0&
0,
#354000000000000
1#
1)
#355000000000000
0#
b1000000000000000 %
0)
b1000000000000000 +
#356000000000000
b0000000000000000 %
1&
b0000000000000000 +
1,
#357000000000000
0&
0,
#358000000000000
1#
1)
#359000000000000
0#
b1000000000000000 %
0)
b1000000000000000 +
#360000000000000
b0000000000000000 %
1&
b0000000000000000 +
1,
#361000000000000
0&
0,
#362000000000000
1#
1)
#363000000000000
0#
b1000000000000000 %
0)
b1000000000000000 +
#364000000000000
b0000000000000000 %
1&
b0000000000000000 +
1,
#365000000000000
0&
0,
#366000000000000
1#
1)
#367000000000000
0#
b1000000000000000 %
0)
b1000000000000000 +
#368000000000000
b0000000000000000 %
1&
b0000000000000000 +
1,
#369000000000000
0&
0,
#370000000000000
1#
1)
#371000000000000
0#
b1000000000000000 %
0)
b1000000000000000 +
#372000000000000
b0000000000000000 %
1&
b0000000000000000 +
1,
#373000000000000
0&
0,
#374000000000000
1#
1)
#375000000000000
0#
b1000000000000000 %
0)
b1000000000000000 +
#376000000000000
b0000000000000000 %
1&
b0000000000000000 +
1,
#377000000000000
0&
0,
#378000000000000
1#
1)
#379000000000000
0#
b1000000000000000 %
0)
b1000000000000000 +
#380000000000000
b0000000000000000 %
1&
b0000000000000000 +
1,
#381000000000000
0&
0,
#382000000000000
1#
1)
#383000000000000
0#
b1000000000000000 %
0)
b1000000000000000 +
#384000000000000
b0000000000000000 %
1&
b0000000000000000 +
1,
#385000000000000
0&
0,
#386000000000000
1#
1)
#387000000000000
0#
b1000000000000000 %
0)
b1000000000000000 +
#388000000000000
b0000000000000000 %
1&
b0000000000000000 +
1,
#389000000000000
0&
0,
#390000000000000
1#
1)
#391000000000000
0#
b1000000000000000 %
0)
b1000000000000000 +
#392000000000000
b0000000000000000 %
1&
b0000000000000000 +
1,
#393000000000000
0&
0,
#394000000000000
1#
1)
#395000000000000
0#
b1000000000000000 %
0)
b1000000000000000 +
#396000000000000
b0000000000000000 %
1&
b0000000000000000 +
1,
#397000000000000
0&
0,
#398000000000000
1#
1)
#399000000000000
0#
b1000000000000000 %
0)
b1000000000000000 +
#400000000000000
b0000000000000000 %
1&
b0000000000000000 +
1,
#401000000000000
0&
0,
#402000000000000
1#
1)
#403000000000000
0#
b1000000000000000 %
0)
b1000000000000000 +
#404000000000000
b0000000000000000 %
1&
b0000000000000000 +
1,
#405000000000000
0&
0,
#406000000000000
1#
1)
#407000000000000
0#
b1000000000000000 %
0)
b1000000000000000 +
#408000000000000
b0000000000000000 %
1&
b0000000000000000 +
1,
#409000000000000
0&
0,
#410000000000000
1#
1)
#411000000000000
0#
b1000000000000000 %
0)
b1000000000000000 +
#412000000000000
b0000000000000000 %
1&
b0000000000000000 +
1,
#413000000000000
0&
0,
#414000000000000
1#
1)
#415000000000000
0#
b1000000000000000 %
0)
b1000000000000000 +
#416000000000000
b0000000000000000 %
1&
b0000000000000000 +
1,
#417000000000000
0&
0,
#418000000000000
1#
1)
#419000000000000
0#
b1000000000000000 %
0)
b1000000000000000 +
#420000000000000
b0000000000000000 %
1&
b0000000000000000 +
1,
#421000000000000
0&
0,
#422000000000000
1#
1)
#423000000000000
0#
b1000000000000000 %
0)
b1000000000000000 +
#424000000000000
b0000000000000000 %
1&
b0000000000000000 +
1,
#425000000000000
0&
0,
#426000000000000
1#
1)
#427000000000000
0#
b1000000000000000 %
0)
b1000000000000000 +
#428000000000000
b0000000000000000 %
1&
b0000000000000000 +
1,
#429000000000000
0&
0,
#430000000000000
1#
1)
#431000000000000
0#
b1000000000000000 %
0)
b1000000000000000 +
#432000000000000
b0000000000000000 %
1&
b0000000000000000 +
1,
#433000000000000
0&
0,
#434000000000000
1#
1)
#435000000000000
0#
b1000000000000000 %
0)
b1000000000000000 +
#436000000000000
b0000000000000000 %
1&
b0000000000000000 +
1,
#437000000000000
0&
0,
#438000000000000
1#
1)
#439000000000000
0#
b1000000000000000 %
0)
b1000000000000000 +
#440000000000000
b0000000000000000 %
1&
b0000000000000000 +
1,
#441000000000000
0&
0,
#442000000000000
1#
1)
#443000000000000
0#
b1000000000000000 %
0)
b1000000000000000 +
#444000000000000
b0000000000000000 %
1&
b0000000000000000 +
1,
#445000000000000
0&
0,
#446000000000000
1#
1)
#447000000000000
0#
b1000000000000000 %
0)
b1000000000000000 +
#448000000000000
b0000000000000000 %
1&
b0000000000000000 +
1,
#449000000000000
0&
0,
#450000000000000
1#
1)
#451000000000000
0#
b1000000000000000 %
0)
b1000000000000000 +
#452000000000000
b0000000000000000 %
1&
b0000000000000000 +
1,
#453000000000000
0&
0,
#454000000000000
1#
1)
#455000000000000
0#
b1000000000000000 %
0)
b1000000000000000 +
#456000000000000
b0000000000000000 %
1&
b0000000000000000 +
1,
#457000000000000
0&
0,
#458000000000000
1#
1)
#459000000000000
0#
b1000000000000000 %
0)
b1000000000000000 +
#460000000000000
b0000000000000000 %
1&
b0000000000000000 +
1,
#461000000000000
0&
0,
#462000000000000
1#
1)
#463000000000000
0#
b1000000000000000 %
0)
b1000000000000000 +
#464000000000000
b0000000000000000 %
1&
b0000000000000000 +
1,
#465000000000000
0&
0,
#466000000000000
1#
1)
#467000000000000
0#
b1000000000000000 %
0)
b1000000000000000 +
#468000000000000
b0000000000000000 %
1&
b0000000000000000 +
1,
#469000000000000
0&
0,
#470000000000000
1#
1)
#471000000000000
0#
b1000000000000000 %
0)
b1000000000000000 +
#472000000000000
b0000000000000000 %
1&
b0000000000000000 +
1,
#473000000000000
0&
0,
#474000000000000
1#
1)
#475000000000000
0#
b1000000000000000 %
0)
b1000000000000000 +
#476000000000000
b0000000000000000 %
1&
b0000000000000000 +
1,
#477000000000000
0&
0,
#478000000000000
1#
1)
#479000000000000
0#
b1000000000000000 %
0)
b1000000000000000 +
#480000000000000
b0000000000000000 %
1&
b0000000000000000 +
1,
#481000000000000
0&
0,
#482000000000000
1#
1)
#483000000000000
0#
b1000000000000000 %
0)
b1000000000000000 +
#484000000000000
b0000000000000000 %
1&
b0000000000000000 +
1,
#485000000000000
0&
0,
#486000000000000
1#
1)
#487000000000000
0#
b1000000000000000 %
0)
b1000000000000000 +
#488000000000000
b0000000000000000 %
1&
b0000000000000000 +
1,
#489000000000000
0&
0,
#490000000000000
1#
1)
#491000000000000
0#
b1000000000000000 %
0)
b1000000000000000 +
#492000000000000
b0000000000000000 %
1&
b0000000000000000 +
1,
#493000000000000
0&
0,
#494000000000000
1#
1)
#495000000000000
0#
b1000000000000000 %
0)
b1000000000000000 +
#496000000000000
b0000000000000000 %
1&
b0000000000000000 +
1,
#497000000000000
0&
0,
#498000000000000
1#
1)
#499000000000000
0#
b1000000000000000 %
0)
b1000000000000000 +
#500000000000000
b0000000000000000 %
1&
b0000000000000000 +
1,
#501000000000000
0&
0,
#502000000000000
1#
1)
#503000000000000
0#
b1000000000000000 %
0)
b1000000000000000 +
#504000000000000
b0000000000000000 %
1&
b0000000000000000 +
1,
#505000000000000
0&
0,
#506000000000000
1#
1)
#507000000000000
0#
b1000000000000000 %
0)
b1000000000000000 +
#508000000000000
b0000000000000000 %
1&
b0000000000000000 +
1,
#509000000000000
0&
0,
#510000000000000
1#
1)
#511000000000000
0#
b1000000000000000 %
0)
b1000000000000000 +
#512000000000000
b0000000000000000 %
1&
b0000000000000000 +
1,
#513000000000000
0&
0,
#514000000000000
1#
1)
#515000000000000
0#
b1000000000000000 %
0)
b1000000000000000 +
#516000000000000
b0000000000000000 %
1&
b0000000000000000 +
1,
#517000000000000
0&
0,
#518000000000000
1#
1)
#519000000000000
0#
b1000000000000000 %
0)
b1000000000000000 +
#520000000000000
b0000000000000000 %
1&
b0000000000000000 +
1,
#521000000000000
0&
0,
#522000000000000
1#
1)
#523000000000000
0#
b1000000000000000 %
0)
b1000000000000000 +
#524000000000000
b0000000000000000 %
1&
b0000000000000000 +
1,
#525000000000000
0&
0,
#526000000000000
1#
1)
#527000000000000
0#
b1000000000000000 %
0)
b1000000000000000 +
#528000000000000
b0000000000000000 %
1&
b0000000000000000 +
1,
#529000000000000
0&
0,
#530000000000000
1#
1)
#531000000000000
0#
b1000000000000000 %
0)
b1000000000000000 +
#532000000000000
b0000000000000000 %
1&
b0000000000000000 +
1,
#533000000000000
0&
0,
#534000000000000
1#
1)
#535000000000000
0#
b1000000000000000 %
0)
b1000000000000000 +
#536000000000000
b0000000000000000 %
1&
b0000000000000000 +
1,
#537000000000000
0&
0,
#538000000000000
1#
1)
#539000000000000
0#
b1000000000000000 %
0)
b1000000000000000 +
#540000000000000
b0000000000000000 %
1&
b0000000000000000 +
1,
#541000000000000
0&
0,
#542000000000000
1#
1)
#543000000000000
0#
b1000000000000000 %
0)
b1000000000000000 +
#544000000000000
b0000000000000000 %
1&
b0000000000000000 +
1,
#545000000000000
0&
0,
#546000000000000
1#
1)
#547000000000000
0#
b1000000000000000 %
0)
b1000000000000000 +
#548000000000000
b0000000000000000 %
1&
b0000000000000000 +
1,
#549000000000000
0&
0,
#550000000000000
1#
1)
#551000000000000
0#
b1000000000000000 %
0)
b1000000000000000 +
#552000000000000
b0000000000000000 %
1&
b0000000000000000 +
1,
#553000000000000
0&
0,
#554000000000000
1#
1)
#555000000000000
0#
b1000000000000000 %
0)
b1000000000000000 +
#556000000000000
b0000000000000000 %
1&
b0000000000000000 +
1,
#557000000000000
0&
0,
#558000000000000
1#
1)
#559000000000000
0#
b1000000000000000 %
0)
b1000000000000000 +
#560000000000000
b0000000000000000 %
1&
b0000000000000000 +
1,
#561000000000000
0&
0,
#562000000000000
1#
1)
#563000000000000
0#
b1000000000000000 %
0)
b1000000000000000 +
#564000000000000
b0000000000000000 %
1&
b0000000000000000 +
1,
#565000000000000
0&
0,
#566000000000000
1#
1)
#567000000000000
0#
b1000000000000000 %
0)
b1000000000000000 +
#568000000000000
b0000000000000000 %
1&
b0000000000000000 +
1,
#569000000000000
0&
0,
#570000000000000
1#
1)
