ALU.vhd
library IEEE;
use IEEE.std_logic_1164.all;
use IEEE.numeric_std.all;

entity ALU is
    port (
        ALUOp: in STD_LOGIC_VECTOR(3 downto 0) := "0000";
        A: in STD_LOGIC_VECTOR(15 downto 0) := "0000000000000000";
        B: in STD_LOGIC_VECTOR(15 downto 0) := "0000000000000000";
        isBranch: out STD_LOGIC := '0';
        outToMemory: out STD_LOGIC_VECTOR(9 downto 0) := "0000000000";
        outToRegMux: out STD_LOGIC_VECTOR(15 downto 0) := "0000000000000000";
        reset: in STD_LOGIC := '1'
    );
end ALU;

architecture Behavioral of ALU is

begin
    -- Asynchronous reset
    process (reset, ALUOp, A, B)
        begin
            if (reset = '1') then
                isBranch <= '0';
                outToMemory <= "0000000000";
                outToRegMux <= "0000000000000000";
                report "reset on";
            else
                case ALUOp is
                    when "0000" => -- halt
                        -- Do nothing
                    when "0001" => -- ld
                        -- Send out last 10 bits for address
                        outToMemory <= A(9 downto 0); -- Fetch r1
                        -- Reset outputs
                        isBranch <= '0';
                        outToRegMux <= "0000000000000000";
                    when "0010" => -- ldi
                        -- Handled internally through register file
                    when "0011" => -- sd
                        -- Send out last 10 bits of r2
                        outToMemory <= B(9 downto 0);
                        -- Reset outputs
                        isBranch <= '0';
                        outToRegMux <= "0000000000000000";
                    when "0100" => -- mv
                        -- Pass contents of r1 to outToRegMux
                        outToRegMux <= A;
                        -- Reset outputs
                        isBranch <= '0';
                        outToMemory <= "0000000000";
                    when "0101" => -- add
                        outToRegMux <= STD_LOGIC_VECTOR(signed(A) + signed(B));
                        -- Reset outputs
                        isBranch <= '0';
                        outToMemory <= "0000000000";
                    when "0110" => -- sub
                        outToRegMux <= STD_LOGIC_VECTOR(signed(A) - signed(B));
                        -- Reset outputs
                        isBranch <= '0';
                        outToMemory <= "0000000000";
                    when "0111" => -- sll
                        outToRegMux <= STD_LOGIC_VECTOR(shift_left(signed(A), to_integer(signed(B))));
                        -- Reset outputs
                        isBranch <= '0';
                        outToMemory <= "0000000000";
                    when "1000" => -- srl
                        outToRegMux <= STD_LOGIC_VECTOR(shift_right(signed(A), to_integer(signed(B))));
                        -- Reset outputs
                        isBranch <= '0';
                        outToMemory <= "0000000000";
                    when "1001" => -- and
                        outToRegMux <= A and B;
                        -- Reset outputs
                        isBranch <= '0';
                        outToMemory <= "0000000000";
                    when "1010" => -- or
                        outToRegMux <= A or B;
                        -- Reset outputs
                        isBranch <= '0';
                        outToMemory <= "0000000000";
                    when "1011" => -- beq
                        if (A = B) then
                            isBranch <= '1';
                        else
                            isBranch <= '0';
                        end if;
                        outToRegMux <= "0000000000000000";
                        outToMemory <= "0000000000";
                    when "1100" => -- blt
                        if (signed(A) < signed(B)) then
                            isBranch <= '1';
                        else
                            isBranch <= '0';
                        end if;
                        outToRegMux <= "0000000000000000";
                        outToMemory <= "0000000000";
                    when "1101" => -- bge
                        if (signed(A) >= signed(B)) then
                            isBranch <= '1';
                        else
                            isBranch <= '0';
                        end if;
                        outToRegMux <= "0000000000000000";
                        outToMemory <= "0000000000";
                    when "1110" => -- jal
                        isBranch <= '1';
                        outToRegMux <= "0000000000000000";
                        outToMemory <= "0000000000";
                    when "1111" => -- jalr
                        isBranch <= '1';
                        outToRegMux <= A;
                        outToMemory <= "0000000000";
                    when others =>
                        -- Do nothing
                        report "Invalid opcode";
                end case;
            end if;

    end process;

end Behavioral;

ALU/ALU_tb.vhd
library IEEE;
use IEEE.std_logic_1164.all;
use IEEE.numeric_std.all;

entity t_alu is
end t_alu;

architecture behavior of t_alu is
    component ALU is 
        port(
            ALUOp: in STD_LOGIC_VECTOR(3 downto 0) := "0000";
            A: in STD_LOGIC_VECTOR(15 downto 0) := "0000000000000000";
            B: in STD_LOGIC_VECTOR(15 downto 0) := "0000000000000000";
            isBranch: out STD_LOGIC := '0';
            outToMemory: out STD_LOGIC_VECTOR(9 downto 0) := "0000000000";
            outToRegMux: out STD_LOGIC_VECTOR(15 downto 0) := "0000000000000000";
            reset: in STD_LOGIC := '1'
        );
    end component ALU;

    signal ALUOp_t: STD_LOGIC_VECTOR(3 downto 0);
    signal A_t: STD_LOGIC_VECTOR(15 downto 0);
    signal B_t: STD_LOGIC_VECTOR(15 downto 0);
    signal isBranch_t: STD_LOGIC;
    signal outToMemory_t: STD_LOGIC_VECTOR(9 downto 0);
    signal outToRegMux_t: STD_LOGIC_VECTOR(15 downto 0);
    signal reset_t: STD_LOGIC;

    begin
        math: ALU
        port map(
            ALUOp => ALUOp_t,
            A => A_t,
            B => B_t,
            isBranch => isBranch_t,
            outToMemory => outToMemory_t,
            outToRegMux => outToRegMux_t,
            reset => reset_t
        );
        process
            begin
                -- Test reset
                reset_t <= '1';
                wait for 1 ms;
                reset_t <= '0';
                assert outToMemory_t = "0000000000";
                assert outToRegMux_t = "0000000000000000";
                wait for 1 ms;

                -- Test writing to ld
                ALUOp_t <= "0001";
                -- Only last 10 bits make address
                A_t <= "0000001000000000";
                wait for 1 ms;
                assert outToRegMux_t = "0000000000000000";
                wait for 1 ms;

                -- Test sd
                ALUOp_t <= "0011";
                B_t <= "0000000000001111";
                wait for 1 ms;
                assert outToMemory_t = "0000001111";
                wait for 1 ms;

                -- Test mv
                ALUOp_t <= "0100";
                A_t <= "0000000000010000";
                wait for 1 ms;
                assert outToMemory_t = "0000000000";
                wait for 1 ms;

                -- Test add
                ALUOp_t <= "0101";
                A_t <= "0000000000000101";
                B_t <= "0000000000001010";
                wait for 1 ms;
                assert outToRegMux_t = "0000000000001111";
                wait for 1 ms;

                -- Test sub
                ALUOp_t <= "0110";
                A_t <= "0000000000000101";
                B_t <= "0000000000001010";
                wait for 1 ms;
                assert outToRegMux_t = "1111111111111011";
                wait for 1 ms;

                -- Test sll
                ALUOp_t <= "0111";
                A_t <= "1010101010101010";
                B_t <= "0000000000000001";
                wait for 1 ms;
                assert outToRegMux_t = "0101010101010100";
                wait for 1 ms;

                -- Test srl
                ALUOp_t <= "1000";
                A_t <= "1010101010101010";
                B_t <= "0000000000000001";
                wait for 1 ms;
                assert outToRegMux_t = "1101010101010101"; -- Pad with 1
                wait for 1 ms;
                
                -- Test and
                ALUOp_t <= "1001";
                A_t <= "0000000010101111";
                B_t <= "0000000001101111";
                wait for 1 ms;
                assert outToRegMux_t = "0000000000101111";
                wait for 1 ms;
                -- Test overflow
                A_t <= "1111111111111100";
                B_t <= "1111111111111101";
                wait for 1 ms;
                assert outToRegMux_t = "1111111111111100";
                wait for 1 ms;

                -- Test or
                ALUOp_t <= "1010";
                A_t <= "0000000010101111";
                B_t <= "0000000001101111";
                wait for 1 ms;
                assert outToRegMux_t = "0000000011101111";
                wait for 1 ms;

                -- Test beq
                ALUOp_t <= "1011";
                A_t <= "0000000010101111";
                B_t <= "0000000010101111";
                wait for 1 ms;
                assert isBranch_t = '1';
                wait for 1 ms;

                -- Test beq
                ALUOp_t <= "1011";
                A_t <= "0000000010101111";
                B_t <= "0000000010101111";
                wait for 1 ms;
                assert isBranch_t = '1';
                wait for 1 ms;

                -- Test blt
                ALUOp_t <= "1100";
                wait for 1 ms;
                assert isBranch_t = '0';
                wait for 1 ms;

                -- Test bge
                ALUOp_t <= "1101";
                wait for 1 ms;
                assert isBranch_t = '1';
                wait for 1 ms;
                
                -- Test jal
                ALUOp_t <= "1110";
                A_t <= "1111111111111111";
                wait for 1 ms;
                assert outToRegMux_t = "0000000000000000";
                assert isBranch_t = '1';
                wait for 1 ms;

                -- Test jalr
                ALUOp_t <= "1111";
                A_t <= "1111111111111111";
                wait for 1 ms;
                assert outToRegMux_t = "1111111111111111";
                assert isBranch_t = '1';
                wait for 1 ms;

                report "Test complete";
        end process;


end behavior;

ALU/alu.vcd
$date
  Fri Mar 20 18:24:58 2020
$end
$version
  GHDL v0
$end
$timescale
  1 fs
$end
$scope module standard $end
$upscope $end
$scope module std_logic_1164 $end
$upscope $end
$scope module numeric_std $end
$upscope $end
$scope module t_alu $end
$var reg 4 ! aluop_t[3:0] $end
$var reg 16 " a_t[15:0] $end
$var reg 16 # b_t[15:0] $end
$var reg 1 $ isbranch_t $end
$var reg 10 % outtomemory_t[9:0] $end
$var reg 16 & outtoregmux_t[15:0] $end
$var reg 1 ' reset_t $end
$scope module math $end
$var reg 4 ( aluop[3:0] $end
$var reg 16 ) a[15:0] $end
$var reg 16 * b[15:0] $end
$var reg 1 + isbranch $end
$var reg 10 , outtomemory[9:0] $end
$var reg 16 - outtoregmux[15:0] $end
$var reg 1 . reset $end
$upscope $end
$upscope $end
$enddefinitions $end
#0
bUUUU !
bUUUUUUUUUUUUUUUU "
bUUUUUUUUUUUUUUUU #
0$
b0000000000 %
b0000000000000000 &
1'
bUUUU (
bUUUUUUUUUUUUUUUU )
bUUUUUUUUUUUUUUUU *
0+
b0000000000 ,
b0000000000000000 -
1.
#1000000000000
0'
0.
#2000000000000
b0001 !
b0000001000000000 "
b1000000000 %
b0001 (
b0000001000000000 )
b1000000000 ,
#3000000000000
#4000000000000
b0011 !
b0000000000001111 #
b0000001111 %
b0011 (
b0000000000001111 *
b0000001111 ,
#5000000000000
#6000000000000
b0100 !
b0000000000010000 "
b0000000000 %
b0000000000010000 &
b0100 (
b0000000000010000 )
b0000000000 ,
b0000000000010000 -
#7000000000000
#8000000000000
b0101 !
b0000000000000101 "
b0000000000001010 #
b0000000000001111 &
b0101 (
b0000000000000101 )
b0000000000001010 *
b0000000000001111 -
#9000000000000
#10000000000000
b0110 !
b1111111111111011 &
b0110 (
b1111111111111011 -
#11000000000000
#12000000000000
b0111 !
b1010101010101010 "
b0000000000000001 #
b0101010101010100 &
b0111 (
b1010101010101010 )
b0000000000000001 *
b0101010101010100 -
#13000000000000
#14000000000000
b1000 !
b1101010101010101 &
b1000 (
b1101010101010101 -
#15000000000000
#16000000000000
b1001 !
b0000000010101111 "
b0000000001101111 #
b0000000000101111 &
b1001 (
b0000000010101111 )
b0000000001101111 *
b0000000000101111 -
#17000000000000
#18000000000000
b1111111111111100 "
b1111111111111101 #
b1111111111111100 &
b1111111111111100 )
b1111111111111101 *
b1111111111111100 -
#19000000000000
#20000000000000
b1010 !
b0000000010101111 "
b0000000001101111 #
b0000000011101111 &
b1010 (
b0000000010101111 )
b0000000001101111 *
b0000000011101111 -
#21000000000000
#22000000000000
b1011 !
b0000000010101111 #
1$
b0000000000000000 &
b1011 (
b0000000010101111 *
1+
b0000000000000000 -
#23000000000000
#24000000000000
#25000000000000
#26000000000000
b1100 !
0$
b1100 (
0+
#27000000000000
#28000000000000
b1101 !
1$
b1101 (
1+
#29000000000000
#30000000000000
b1110 !
b1111111111111111 "
b1110 (
b1111111111111111 )
#31000000000000
#32000000000000
b1111 !
b1111111111111111 &
b1111 (
b1111111111111111 -
#33000000000000
#34000000000000
0$
b0000000000000000 &
1'
0+
b0000000000000000 -
1.
#35000000000000
1$
b1111111111111111 &
0'
1+
b1111111111111111 -
0.
#36000000000000
b0001 !
b0000001000000000 "
0$
b1000000000 %
b0000000000000000 &
b0001 (
b0000001000000000 )
0+
b1000000000 ,
b0000000000000000 -
#37000000000000
#38000000000000
b0011 !
b0000000000001111 #
b0000001111 %
b0011 (
b0000000000001111 *
b0000001111 ,
#39000000000000
#40000000000000
b0100 !
b0000000000010000 "
b0000000000 %
b0000000000010000 &
b0100 (
b0000000000010000 )
b0000000000 ,
b0000000000010000 -
#41000000000000
#42000000000000
b0101 !
b0000000000000101 "
b0000000000001010 #
b0000000000001111 &
b0101 (
b0000000000000101 )
b0000000000001010 *
b0000000000001111 -
#43000000000000
#44000000000000
b0110 !
b1111111111111011 &
b0110 (
b1111111111111011 -
#45000000000000
#46000000000000
b0111 !
b1010101010101010 "
b0000000000000001 #
b0101010101010100 &
b0111 (
b1010101010101010 )
b0000000000000001 *
b0101010101010100 -
#47000000000000
#48000000000000
b1000 !
b1101010101010101 &
b1000 (
b1101010101010101 -
#49000000000000
#50000000000000
b1001 !
b0000000010101111 "
b0000000001101111 #
b0000000000101111 &
b1001 (
b0000000010101111 )
b0000000001101111 *
b0000000000101111 -
#51000000000000
#52000000000000
b1111111111111100 "
b1111111111111101 #
b1111111111111100 &
b1111111111111100 )
b1111111111111101 *
b1111111111111100 -
#53000000000000
#54000000000000
b1010 !
b0000000010101111 "
b0000000001101111 #
b0000000011101111 &
b1010 (
b0000000010101111 )
b0000000001101111 *
b0000000011101111 -
#55000000000000
#56000000000000
b1011 !
b0000000010101111 #
1$
b0000000000000000 &
b1011 (
b0000000010101111 *
1+
b0000000000000000 -
#57000000000000
#58000000000000
#59000000000000
#60000000000000
b1100 !
0$
b1100 (
0+
#61000000000000
#62000000000000
b1101 !
1$
b1101 (
1+
#63000000000000
#64000000000000
b1110 !
b1111111111111111 "
b1110 (
b1111111111111111 )
#65000000000000
#66000000000000
b1111 !
b1111111111111111 &
b1111 (
b1111111111111111 -
#67000000000000
#68000000000000
0$
b0000000000000000 &
1'
0+
b0000000000000000 -
1.
#69000000000000
1$
b1111111111111111 &
0'
1+
b1111111111111111 -
0.
#70000000000000
b0001 !
b0000001000000000 "
0$
b1000000000 %
b0000000000000000 &
b0001 (
b0000001000000000 )
0+
b1000000000 ,
b0000000000000000 -
#71000000000000
#72000000000000
b0011 !
b0000000000001111 #
b0000001111 %
b0011 (
b0000000000001111 *
b0000001111 ,
#73000000000000
#74000000000000
b0100 !
b0000000000010000 "
b0000000000 %
b0000000000010000 &
b0100 (
b0000000000010000 )
b0000000000 ,
b0000000000010000 -
#75000000000000
#76000000000000
b0101 !
b0000000000000101 "
b0000000000001010 #
b0000000000001111 &
b0101 (
b0000000000000101 )
b0000000000001010 *
b0000000000001111 -
#77000000000000
#78000000000000
b0110 !
b1111111111111011 &
b0110 (
b1111111111111011 -
#79000000000000
#80000000000000
b0111 !
b1010101010101010 "
b0000000000000001 #
b0101010101010100 &
b0111 (
b1010101010101010 )
b0000000000000001 *
b0101010101010100 -
#81000000000000
#82000000000000
b1000 !
b1101010101010101 &
b1000 (
b1101010101010101 -
#83000000000000
#84000000000000
b1001 !
b0000000010101111 "
b0000000001101111 #
b0000000000101111 &
b1001 (
b0000000010101111 )
b0000000001101111 *
b0000000000101111 -
#85000000000000
#86000000000000
b1111111111111100 "
b1111111111111101 #
b1111111111111100 &
b1111111111111100 )
b1111111111111101 *
b1111111111111100 -
#87000000000000
#88000000000000
b1010 !
b0000000010101111 "
b0000000001101111 #
b0000000011101111 &
b1010 (
b0000000010101111 )
b0000000001101111 *
b0000000011101111 -
#89000000000000
#90000000000000
b1011 !
b0000000010101111 #
1$
b0000000000000000 &
b1011 (
b0000000010101111 *
1+
b0000000000000000 -
#91000000000000
#92000000000000
#93000000000000
#94000000000000
b1100 !
0$
b1100 (
0+
#95000000000000
#96000000000000
b1101 !
1$
b1101 (
1+
#97000000000000
#98000000000000
b1110 !
b1111111111111111 "
b1110 (
b1111111111111111 )
#99000000000000
#100000000000000
b1111 !
b1111111111111111 &
b1111 (
b1111111111111111 -
#101000000000000
#102000000000000
0$
b0000000000000000 &
1'
0+
b0000000000000000 -
1.
#103000000000000
1$
b1111111111111111 &
0'
1+
b1111111111111111 -
0.
#104000000000000
b0001 !
b0000001000000000 "
0$
b1000000000 %
b0000000000000000 &
b0001 (
b0000001000000000 )
0+
b1000000000 ,
b0000000000000000 -
#105000000000000
#106000000000000
b0011 !
b0000000000001111 #
b0000001111 %
b0011 (
b0000000000001111 *
b0000001111 ,
#107000000000000
#108000000000000
b0100 !
b0000000000010000 "
b0000000000 %
b0000000000010000 &
b0100 (
b0000000000010000 )
b0000000000 ,
b0000000000010000 -
#109000000000000
#110000000000000
b0101 !
b0000000000000101 "
b0000000000001010 #
b0000000000001111 &
b0101 (
b0000000000000101 )
b0000000000001010 *
b0000000000001111 -
#111000000000000
#112000000000000
b0110 !
b1111111111111011 &
b0110 (
b1111111111111011 -
#113000000000000
#114000000000000
b0111 !
b1010101010101010 "
b0000000000000001 #
b0101010101010100 &
b0111 (
b1010101010101010 )
b0000000000000001 *
b0101010101010100 -
#115000000000000
#116000000000000
b1000 !
b1101010101010101 &
b1000 (
b1101010101010101 -
#117000000000000
#118000000000000
b1001 !
b0000000010101111 "
b0000000001101111 #
b0000000000101111 &
b1001 (
b0000000010101111 )
b0000000001101111 *
b0000000000101111 -
#119000000000000
#120000000000000
b1111111111111100 "
b1111111111111101 #
b1111111111111100 &
b1111111111111100 )
b1111111111111101 *
b1111111111111100 -
#121000000000000
#122000000000000
b1010 !
b0000000010101111 "
b0000000001101111 #
b0000000011101111 &
b1010 (
b0000000010101111 )
b0000000001101111 *
b0000000011101111 -
#123000000000000
#124000000000000
b1011 !
b0000000010101111 #
1$
b0000000000000000 &
b1011 (
b0000000010101111 *
1+
b0000000000000000 -
#125000000000000
#126000000000000
#127000000000000
#128000000000000
b1100 !
0$
b1100 (
0+
#129000000000000
#130000000000000
b1101 !
1$
b1101 (
1+
#131000000000000
#132000000000000
b1110 !
b1111111111111111 "
b1110 (
b1111111111111111 )
#133000000000000
#134000000000000
b1111 !
b1111111111111111 &
b1111 (
b1111111111111111 -
#135000000000000
#136000000000000
0$
b0000000000000000 &
1'
0+
b0000000000000000 -
1.
#137000000000000
1$
b1111111111111111 &
0'
1+
b1111111111111111 -
0.
#138000000000000
b0001 !
b0000001000000000 "
0$
b1000000000 %
b0000000000000000 &
b0001 (
b0000001000000000 )
0+
b1000000000 ,
b0000000000000000 -
#139000000000000
#140000000000000
b0011 !
b0000000000001111 #
b0000001111 %
b0011 (
b0000000000001111 *
b0000001111 ,
#141000000000000
#142000000000000
b0100 !
b0000000000010000 "
b0000000000 %
b0000000000010000 &
b0100 (
b0000000000010000 )
b0000000000 ,
b0000000000010000 -
#143000000000000
#144000000000000
b0101 !
b0000000000000101 "
b0000000000001010 #
b0000000000001111 &
b0101 (
b0000000000000101 )
b0000000000001010 *
b0000000000001111 -
#145000000000000
#146000000000000
b0110 !
b1111111111111011 &
b0110 (
b1111111111111011 -
#147000000000000
#148000000000000
b0111 !
b1010101010101010 "
b0000000000000001 #
b0101010101010100 &
b0111 (
b1010101010101010 )
b0000000000000001 *
b0101010101010100 -
#149000000000000
#150000000000000
b1000 !
b1101010101010101 &
b1000 (
b1101010101010101 -
#151000000000000
#152000000000000
b1001 !
b0000000010101111 "
b0000000001101111 #
b0000000000101111 &
b1001 (
b0000000010101111 )
b0000000001101111 *
b0000000000101111 -
#153000000000000
#154000000000000
b1111111111111100 "
b1111111111111101 #
b1111111111111100 &
b1111111111111100 )
b1111111111111101 *
b1111111111111100 -
#155000000000000
#156000000000000
b1010 !
b0000000010101111 "
b0000000001101111 #
b0000000011101111 &
b1010 (
b0000000010101111 )
b0000000001101111 *
b0000000011101111 -
#157000000000000
#158000000000000
b1011 !
b0000000010101111 #
1$
b0000000000000000 &
b1011 (
b0000000010101111 *
1+
b0000000000000000 -
#159000000000000
#160000000000000
#161000000000000
#162000000000000
b1100 !
0$
b1100 (
0+
#163000000000000
#164000000000000
b1101 !
1$
b1101 (
1+
#165000000000000
#166000000000000
b1110 !
b1111111111111111 "
b1110 (
b1111111111111111 )
#167000000000000
#168000000000000
b1111 !
b1111111111111111 &
b1111 (
b1111111111111111 -
#169000000000000
#170000000000000
0$
b0000000000000000 &
1'
0+
b0000000000000000 -
1.
#171000000000000
1$
b1111111111111111 &
0'
1+
b1111111111111111 -
0.
#172000000000000
b0001 !
b0000001000000000 "
0$
b1000000000 %
b0000000000000000 &
b0001 (
b0000001000000000 )
0+
b1000000000 ,
b0000000000000000 -
#173000000000000
#174000000000000
b0011 !
b0000000000001111 #
b0000001111 %
b0011 (
b0000000000001111 *
b0000001111 ,
#175000000000000
#176000000000000
b0100 !
b0000000000010000 "
b0000000000 %
b0000000000010000 &
b0100 (
b0000000000010000 )
b0000000000 ,
b0000000000010000 -
#177000000000000
#178000000000000
b0101 !
b0000000000000101 "
b0000000000001010 #
b0000000000001111 &
b0101 (
b0000000000000101 )
b0000000000001010 *
b0000000000001111 -
#179000000000000
#180000000000000
b0110 !
b1111111111111011 &
b0110 (
b1111111111111011 -
#181000000000000
#182000000000000
b0111 !
b1010101010101010 "
b0000000000000001 #
b0101010101010100 &
b0111 (
b1010101010101010 )
b0000000000000001 *
b0101010101010100 -
#183000000000000
#184000000000000
b1000 !
b1101010101010101 &
b1000 (
b1101010101010101 -
#185000000000000
#186000000000000
b1001 !
b0000000010101111 "
b0000000001101111 #
b0000000000101111 &
b1001 (
b0000000010101111 )
b0000000001101111 *
b0000000000101111 -
#187000000000000
#188000000000000
b1111111111111100 "
b1111111111111101 #
b1111111111111100 &
b1111111111111100 )
b1111111111111101 *
b1111111111111100 -
#189000000000000
#190000000000000
b1010 !
b0000000010101111 "
b0000000001101111 #
b0000000011101111 &
b1010 (
b0000000010101111 )
b0000000001101111 *
b0000000011101111 -
#191000000000000
#192000000000000
b1011 !
b0000000010101111 #
1$
b0000000000000000 &
b1011 (
b0000000010101111 *
1+
b0000000000000000 -
#193000000000000
#194000000000000
#195000000000000
#196000000000000
b1100 !
0$
b1100 (
0+
#197000000000000
#198000000000000
b1101 !
1$
b1101 (
1+
#199000000000000
#200000000000000
b1110 !
b1111111111111111 "
b1110 (
b1111111111111111 )
#201000000000000
#202000000000000
b1111 !
b1111111111111111 &
b1111 (
b1111111111111111 -
#203000000000000
#204000000000000
0$
b0000000000000000 &
1'
0+
b0000000000000000 -
1.
#205000000000000
1$
b1111111111111111 &
0'
1+
b1111111111111111 -
0.
#206000000000000
b0001 !
b0000001000000000 "
0$
b1000000000 %
b0000000000000000 &
b0001 (
b0000001000000000 )
0+
b1000000000 ,
b0000000000000000 -
#207000000000000
#208000000000000
b0011 !
b0000000000001111 #
b0000001111 %
b0011 (
b0000000000001111 *
b0000001111 ,
#209000000000000
#210000000000000
b0100 !
b0000000000010000 "
b0000000000 %
b0000000000010000 &
b0100 (
b0000000000010000 )
b0000000000 ,
b0000000000010000 -
#211000000000000
#212000000000000
b0101 !
b0000000000000101 "
b0000000000001010 #
b0000000000001111 &
b0101 (
b0000000000000101 )
b0000000000001010 *
b0000000000001111 -
#213000000000000
#214000000000000
b0110 !
b1111111111111011 &
b0110 (
b1111111111111011 -
#215000000000000
#216000000000000
b0111 !
b1010101010101010 "
b0000000000000001 #
b0101010101010100 &
b0111 (
b1010101010101010 )
b0000000000000001 *
b0101010101010100 -
#217000000000000
#218000000000000
b1000 !
b1101010101010101 &
b1000 (
b1101010101010101 -
#219000000000000
#220000000000000
b1001 !
b0000000010101111 "
b0000000001101111 #
b0000000000101111 &
b1001 (
b0000000010101111 )
b0000000001101111 *
b0000000000101111 -
#221000000000000
#222000000000000
b1111111111111100 "
b1111111111111101 #
b1111111111111100 &
b1111111111111100 )
b1111111111111101 *
b1111111111111100 -
#223000000000000
#224000000000000
b1010 !
b0000000010101111 "
b0000000001101111 #
b0000000011101111 &
b1010 (
b0000000010101111 )
b0000000001101111 *
b0000000011101111 -
#225000000000000
#226000000000000
b1011 !
b0000000010101111 #
1$
b0000000000000000 &
b1011 (
b0000000010101111 *
1+
b0000000000000000 -
#227000000000000
#228000000000000
#229000000000000
#230000000000000
b1100 !
0$
b1100 (
0+
#231000000000000
#232000000000000
b1101 !
1$
b1101 (
1+
#233000000000000
#234000000000000
b1110 !
b1111111111111111 "
b1110 (
b1111111111111111 )
#235000000000000
#236000000000000
b1111 !
b1111111111111111 &
b1111 (
b1111111111111111 -
#237000000000000
#238000000000000
0$
b0000000000000000 &
1'
0+
b0000000000000000 -
1.
#239000000000000
1$
b1111111111111111 &
0'
1+
b1111111111111111 -
0.
#240000000000000
b0001 !
b0000001000000000 "
0$
b1000000000 %
b0000000000000000 &
b0001 (
b0000001000000000 )
0+
b1000000000 ,
b0000000000000000 -
#241000000000000
#242000000000000
b0011 !
b0000000000001111 #
b0000001111 %
b0011 (
b0000000000001111 *
b0000001111 ,
#243000000000000
#244000000000000
b0100 !
b0000000000010000 "
b0000000000 %
b0000000000010000 &
b0100 (
b0000000000010000 )
b0000000000 ,
b0000000000010000 -
#245000000000000
#246000000000000
b0101 !
b0000000000000101 "
b0000000000001010 #
b0000000000001111 &
b0101 (
b0000000000000101 )
b0000000000001010 *
b0000000000001111 -
#247000000000000
#248000000000000
b0110 !
b1111111111111011 &
b0110 (
b1111111111111011 -
#249000000000000
#250000000000000
b0111 !
b1010101010101010 "
b0000000000000001 #
b0101010101010100 &
b0111 (
b1010101010101010 )
b0000000000000001 *
b0101010101010100 -
#251000000000000
#252000000000000
b1000 !
b1101010101010101 &
b1000 (
b1101010101010101 -
#253000000000000
#254000000000000
b1001 !
b0000000010101111 "
b0000000001101111 #
b0000000000101111 &
b1001 (
b0000000010101111 )
b0000000001101111 *
b0000000000101111 -
#255000000000000
#256000000000000
b1111111111111100 "
b1111111111111101 #
b1111111111111100 &
b1111111111111100 )
b1111111111111101 *
b1111111111111100 -
#257000000000000
#258000000000000
b1010 !
b0000000010101111 "
b0000000001101111 #
b0000000011101111 &
b1010 (
b0000000010101111 )
b0000000001101111 *
b0000000011101111 -
#259000000000000
#260000000000000
b1011 !
b0000000010101111 #
1$
b0000000000000000 &
b1011 (
b0000000010101111 *
1+
b0000000000000000 -
#261000000000000
#262000000000000
#263000000000000
#264000000000000
b1100 !
0$
b1100 (
0+
#265000000000000
#266000000000000
b1101 !
1$
b1101 (
1+
#267000000000000
#268000000000000
b1110 !
b1111111111111111 "
b1110 (
b1111111111111111 )
#269000000000000
#270000000000000
b1111 !
b1111111111111111 &
b1111 (
b1111111111111111 -
#271000000000000
#272000000000000
0$
b0000000000000000 &
1'
0+
b0000000000000000 -
1.
#273000000000000
1$
b1111111111111111 &
0'
1+
b1111111111111111 -
0.
#274000000000000
b0001 !
b0000001000000000 "
0$
b1000000000 %
b0000000000000000 &
b0001 (
b0000001000000000 )
0+
b1000000000 ,
b0000000000000000 -
#275000000000000
#276000000000000
b0011 !
b0000000000001111 #
b0000001111 %
b0011 (
b0000000000001111 *
b0000001111 ,
#277000000000000
#278000000000000
b0100 !
b0000000000010000 "
b0000000000 %
b0000000000010000 &
b0100 (
b0000000000010000 )
b0000000000 ,
b0000000000010000 -
#279000000000000
#280000000000000
b0101 !
b0000000000000101 "
b0000000000001010 #
b0000000000001111 &
b0101 (
b0000000000000101 )
b0000000000001010 *
b0000000000001111 -
#281000000000000
#282000000000000
b0110 !
b1111111111111011 &
b0110 (
b1111111111111011 -
#283000000000000
#284000000000000
b0111 !
b1010101010101010 "
b0000000000000001 #
b0101010101010100 &
b0111 (
b1010101010101010 )
b0000000000000001 *
b0101010101010100 -
#285000000000000
#286000000000000
b1000 !
b1101010101010101 &
b1000 (
b1101010101010101 -
#287000000000000
#288000000000000
b1001 !
b0000000010101111 "
b0000000001101111 #
b0000000000101111 &
b1001 (
b0000000010101111 )
b0000000001101111 *
b0000000000101111 -
#289000000000000
#290000000000000
b1111111111111100 "
b1111111111111101 #
b1111111111111100 &
b1111111111111100 )
b1111111111111101 *
b1111111111111100 -
#291000000000000
#292000000000000
b1010 !
b0000000010101111 "
b0000000001101111 #
b0000000011101111 &
b1010 (
b0000000010101111 )
b0000000001101111 *
b0000000011101111 -
#293000000000000
#294000000000000
b1011 !
b0000000010101111 #
1$
b0000000000000000 &
b1011 (
b0000000010101111 *
1+
b0000000000000000 -
#295000000000000
#296000000000000
#297000000000000
#298000000000000
b1100 !
0$
b1100 (
0+
#299000000000000
#300000000000000
b1101 !
1$
b1101 (
1+
#301000000000000
#302000000000000
b1110 !
b1111111111111111 "
b1110 (
b1111111111111111 )
#303000000000000
#304000000000000
b1111 !
b1111111111111111 &
b1111 (
b1111111111111111 -
#305000000000000
#306000000000000
0$
b0000000000000000 &
1'
0+
b0000000000000000 -
1.
#307000000000000
1$
b1111111111111111 &
0'
1+
b1111111111111111 -
0.
#308000000000000
b0001 !
b0000001000000000 "
0$
b1000000000 %
b0000000000000000 &
b0001 (
b0000001000000000 )
0+
b1000000000 ,
b0000000000000000 -
#309000000000000
#310000000000000
b0011 !
b0000000000001111 #
b0000001111 %
b0011 (
b0000000000001111 *
b0000001111 ,
#311000000000000
#312000000000000
b0100 !
b0000000000010000 "
b0000000000 %
b0000000000010000 &
b0100 (
b0000000000010000 )
b0000000000 ,
b0000000000010000 -
#313000000000000
#314000000000000
b0101 !
b0000000000000101 "
b0000000000001010 #
b0000000000001111 &
b0101 (
b0000000000000101 )
b0000000000001010 *
b0000000000001111 -
#315000000000000
#316000000000000
b0110 !
b1111111111111011 &
b0110 (
b1111111111111011 -
#317000000000000
#318000000000000
b0111 !
b1010101010101010 "
b0000000000000001 #
b0101010101010100 &
b0111 (
b1010101010101010 )
b0000000000000001 *
b0101010101010100 -
#319000000000000
#320000000000000
b1000 !
b1101010101010101 &
b1000 (
b1101010101010101 -
#321000000000000
#322000000000000
b1001 !
b0000000010101111 "
b0000000001101111 #
b0000000000101111 &
b1001 (
b0000000010101111 )
b0000000001101111 *
b0000000000101111 -
#323000000000000
#324000000000000
b1111111111111100 "
b1111111111111101 #
b1111111111111100 &
b1111111111111100 )
b1111111111111101 *
b1111111111111100 -
#325000000000000
#326000000000000
b1010 !
b0000000010101111 "
b0000000001101111 #
b0000000011101111 &
b1010 (
b0000000010101111 )
b0000000001101111 *
b0000000011101111 -
#327000000000000
#328000000000000
b1011 !
b0000000010101111 #
1$
b0000000000000000 &
b1011 (
b0000000010101111 *
1+
b0000000000000000 -
#329000000000000
#330000000000000
#331000000000000
#332000000000000
b1100 !
0$
b1100 (
0+
#333000000000000
#334000000000000
b1101 !
1$
b1101 (
1+
#335000000000000
#336000000000000
b1110 !
b1111111111111111 "
b1110 (
b1111111111111111 )
#337000000000000
